fileaccess/__init__.py
fileaccess/fileaccess.py
fileaccess-0.2.22.dist-info/LICENSE
fileaccess-0.2.22.dist-info/METADATA
fileaccess-0.2.22.dist-info/WHEEL
fileaccess-0.2.22.dist-info/top_level.txt
fileaccess-0.2.22.dist-info/RECORD
