Metadata-Version: 2.1
Name: fileaccess
Version: 0.2.22
Summary: A package for easier file access, automatically closes opened file handles, & provides for simple file/directory creation.
Home-page: https://github.com/node0/Fileaccess
Author: Joe Hacobian
Author-email: joehacobian@gmail.com
Classifier: Development Status :: 5 - Production/Stable
Classifier: Intended Audience :: Developers
Classifier: License :: OSI Approved :: MIT License
Classifier: Programming Language :: Python :: 3
Classifier: Programming Language :: Python :: 3.6
Classifier: Programming Language :: Python :: 3.7
Classifier: Programming Language :: Python :: 3.8
Classifier: Programming Language :: Python :: 3.9
Classifier: Programming Language :: Python :: 3.10
Classifier: Programming Language :: Python :: 3.11
License-File: LICENSE
